thermoplotting/__init__.py
thermoplotting/binary.py
thermoplotting/blocks.py
thermoplotting/eci.py
thermoplotting/energy.py
thermoplotting/misc.py
thermoplotting/plot.py
thermoplotting/quaternary.py
thermoplotting/selection.py
thermoplotting/strain.py
thermoplotting/ternary.py
thermoplotting/thermoarray.py
thermoplotting/thermoio.py
thermoplotting/grandcanonical/__init__.py
thermoplotting/grandcanonical/access.py
thermoplotting/grandcanonical/integrate.py
thermoplotting/grandcanonical/runs.py
thermoplotting/split/__init__.py
thermoplotting/split/clustcompare.py
thermoplotting/systems/__init__.py
thermoplotting/systems/systems.py
thermoplotting/xtals/__init__.py
thermoplotting/xtals/lattice.py
thermoplotting-0.1.dist-info/DESCRIPTION.rst
thermoplotting-0.1.dist-info/LICENSE.txt
thermoplotting-0.1.dist-info/METADATA
thermoplotting-0.1.dist-info/RECORD
thermoplotting-0.1.dist-info/WHEEL
thermoplotting-0.1.dist-info/metadata.json
thermoplotting-0.1.dist-info/top_level.txt
